chg_hostname/__init__.py
chg_hostname/__main__.py
chg_hostname/append.py
chg_hostname/backup.py
chg_hostname/parse_host.py
chg_hostname/replace_loopback.py
chg_hostname/restore.py
chg_hostname/run.py
chg_hostname/test.py
chg_hostname/version.py
chg_hostname/utils/__init__.py
chg_hostname/utils/file_util.py
chg_hostname/utils/get_ip.py
chg_hostname/utils/host_entry.py
chg_hostname/utils/host_file_manager.py
chg_hostname/utils/is_admin.py
chg_hostname/utils/parse_config_file.py
chg_hostname/utils/print_table.py
chg_hostname/utils/table.py
chg_hostname-1.0.0.dist-info/METADATA
chg_hostname-1.0.0.dist-info/WHEEL
chg_hostname-1.0.0.dist-info/entry_points.txt
chg_hostname-1.0.0.dist-info/top_level.txt
chg_hostname-1.0.0.dist-info/RECORD
