Metadata-Version: 2.4
Name: chg-hostname
Version: 1.0.0
Summary: The chg_hostname project is a command-line tool designed to manage your system's host file. It allows users to back up the host file, restore it from a backup, and append new host entries based on a provided JSON configuration file (hosts.json). The tool also includes functionality to replace loopback addresses in the provided configuration.
Requires-Python: >=3.11
Requires-Dist: pydantic>=2.11.3
Requires-Dist: rich>=14.0.0
Requires-Dist: typer>=0.15.2
